molzip/__init__.py
molzip/classifier.py
molzip/knn_graph.py
molzip/regressor.py
molzip/featurizers/__init__.py
molzip/featurizers/zip_featurizer.py
molzip/transforms/__init__.py
molzip/transforms/augment_transform.py
molzip/transforms/base_transform.py
molzip/transforms/deepsmiles_transform.py
molzip/transforms/selfies_transform.py
molzip-0.9.2.dist-info/LICENSE
molzip-0.9.2.dist-info/METADATA
molzip-0.9.2.dist-info/WHEEL
molzip-0.9.2.dist-info/top_level.txt
molzip-0.9.2.dist-info/RECORD
