Metadata-Version: 2.1
Name: molzip
Version: 0.9.2
Summary: An implementation of compression-based regression and classification for molecular SMILES.
License: The MIT License (MIT)
Project-URL: Homepage, https://github.com/daenuprobst/molzip
Keywords: chemistry,cheminformatics,SMILES,compression,zip,regression,classification
License-File: LICENSE
Requires-Dist: numpy >=1.22.3
Requires-Dist: descriptastorus >=2.6.1
Requires-Dist: selfies >=2.1.1
Requires-Dist: deepsmiles >=1.0.1
Requires-Dist: scikit-learn >=1.3.1
